cz_convnetional_ticket.py
cz_convnetional_ticket-1.2.0.dist-info/METADATA
cz_convnetional_ticket-1.2.0.dist-info/WHEEL
cz_convnetional_ticket-1.2.0.dist-info/top_level.txt
cz_convnetional_ticket-1.2.0.dist-info/RECORD
