Metadata-Version: 2.1
Name: cz-convnetional-ticket
Version: 1.2.0
Summary: Conventional commits with tickets in changelog
Home-page: UNKNOWN
Author: Gohar Anwar
Author-email: gohar@goharanwar.com
License: MIT
Platform: UNKNOWN
Requires-Dist: commitizen
